reflex_descope_auth/__init__.py
reflex_descope_auth/state.py
reflex_descope_auth/utils.py
reflex_descope_auth-0.1.6.dist-info/licenses/LICENSE
reflex_descope_auth-0.1.6.dist-info/METADATA
reflex_descope_auth-0.1.6.dist-info/WHEEL
reflex_descope_auth-0.1.6.dist-info/top_level.txt
reflex_descope_auth-0.1.6.dist-info/RECORD
