Metadata-Version: 2.4
Name: reflex-descope-auth
Version: 0.1.6
Summary: A Reflex plugin for handling Descope OAuth authentication.
Author-email: Tal Berry <devrel@descope.com>
License-Expression: MIT
Project-URL: Homepage, https://github.com/descope-sample-apps/reflex-descope-auth
Project-URL: Issues, https://github.com/descope-sample-apps/reflex-descope-auth/issues
Classifier: Programming Language :: Python :: 3
Classifier: Operating System :: OS Independent
Requires-Python: >=3.9
License-File: LICENSE
Requires-Dist: reflex>=0.7.14
Requires-Dist: httpx>=0.28.0
Requires-Dist: PyJWT>=2.10.0
Requires-Dist: requests>=2.31.0
Requires-Dist: cryptography
Dynamic: license-file
